aws_sso_config_builder/__about__.py
aws_sso_config_builder/__init__.py
aws_sso_config_builder/gen_config.py
aws_sso_config_builder-0.0.4.dist-info/METADATA
aws_sso_config_builder-0.0.4.dist-info/WHEEL
aws_sso_config_builder-0.0.4.dist-info/entry_points.txt
aws_sso_config_builder-0.0.4.dist-info/licenses/LICENSE.txt
aws_sso_config_builder-0.0.4.dist-info/RECORD
