Metadata-Version: 2.3
Name: aws-sso-config-builder
Version: 0.0.4
Summary: Build AWS CLI config profiles for SSO accounts and roles
Project-URL: Documentation, https://github.com/ajkerrigan/aws-sso-config-builder#readme
Project-URL: Issues, https://github.com/ajkerrigan/aws-sso-config-builder/issues
Project-URL: Source, https://github.com/ajkerrigan/aws-sso-config-builder
Author-email: AJ Kerrigan <aj@speckledmonkey.com>
License-Expression: MIT
License-File: LICENSE.txt
Classifier: Development Status :: 4 - Beta
Classifier: Programming Language :: Python
Classifier: Programming Language :: Python :: 3.7
Classifier: Programming Language :: Python :: 3.8
Classifier: Programming Language :: Python :: 3.9
Classifier: Programming Language :: Python :: 3.10
Classifier: Programming Language :: Python :: 3.11
Classifier: Programming Language :: Python :: 3.12
Classifier: Programming Language :: Python :: Implementation :: CPython
Classifier: Programming Language :: Python :: Implementation :: PyPy
Requires-Python: >=3.7
Requires-Dist: boto3
Requires-Dist: click
Requires-Dist: keyring
Requires-Dist: rich
